apiclienthttp/__init__.py
apiclienthttp/auth.py
apiclienthttp/baseclasses.py
apiclienthttp/client.py
apiclienthttp/constants.py
apiclienthttp/exceptions.py
apiclienthttp/headers.py
apiclienthttp/response.py
apiclienthttp/structures.py
apiclienthttp/urls.py
apiclienthttp/utils.py
api_client_http-1.1.0.dist-info/LICENSE
api_client_http-1.1.0.dist-info/METADATA
api_client_http-1.1.0.dist-info/WHEEL
api_client_http-1.1.0.dist-info/RECORD
