Metadata-Version: 2.3
Name: api-client-http
Version: 1.1.0
Summary: Client for sync/async query HTTP API Services
Author: Igor Voropaev
Author-email: snakework10@gmail.com
Requires-Python: >=3.11,<4.0
Classifier: Programming Language :: Python :: 3
Classifier: Programming Language :: Python :: 3.11
Classifier: Programming Language :: Python :: 3.12
Classifier: Programming Language :: Python :: 3.13
Requires-Dist: httpx (>=0.28,<1.0)
Project-URL: Repository, https://github.com/apiclienthttp/apiclienthttp
